{
	"configurations" : 
	[
		{
			"directories" : 
			[
				{
					"build" : ".",
					"childIndexes" : 
					[
						1
					],
					"minimumCMakeVersion" : 
					{
						"string" : "3.5"
					},
					"projectIndex" : 0,
					"source" : "."
				},
				{
					"build" : "src",
					"minimumCMakeVersion" : 
					{
						"string" : "3.5"
					},
					"parentIndex" : 0,
					"projectIndex" : 0,
					"source" : "src",
					"targetIndexes" : 
					[
						0,
						1
					]
				}
			],
			"name" : "Debug",
			"projects" : 
			[
				{
					"directoryIndexes" : 
					[
						0,
						1
					],
					"name" : "gpu_cqf",
					"targetIndexes" : 
					[
						0,
						1
					]
				}
			],
			"targets" : 
			[
				{
					"directoryIndex" : 1,
					"id" : "cqf::@145eef247bfb46b6828c",
					"jsonFile" : "target-cqf-Debug-530ee4adbd0bbc9889d3.json",
					"name" : "cqf",
					"projectIndex" : 0
				},
				{
					"directoryIndex" : 1,
					"id" : "cqf_core::@145eef247bfb46b6828c",
					"jsonFile" : "target-cqf_core-Debug-3ce3d0ae2c9ca9b0f5a5.json",
					"name" : "cqf_core",
					"projectIndex" : 0
				}
			]
		}
	],
	"kind" : "codemodel",
	"paths" : 
	{
		"build" : "C:/Users/ericw/Desktop/cqf/out/build/x64-Debug (default)",
		"source" : "C:/Users/ericw/Desktop/cqf"
	},
	"version" : 
	{
		"major" : 2,
		"minor" : 0
	}
}
